keycipher/__init__.py
keycipher/main.py
keycipher-1.0.0.dist-info/METADATA
keycipher-1.0.0.dist-info/WHEEL
keycipher-1.0.0.dist-info/top_level.txt
keycipher-1.0.0.dist-info/RECORD
